benfords/__init__.py
benfords-1.0.2.dist-info/LICENSE
benfords-1.0.2.dist-info/METADATA
benfords-1.0.2.dist-info/WHEEL
benfords-1.0.2.dist-info/top_level.txt
benfords-1.0.2.dist-info/RECORD
