Metadata-Version: 2.1
Name: benfords
Version: 1.0.2
Summary: Provides a series of functions to make Benford's Law usage more convenient.
Home-page: https://github.com/danielmccarville/Benfords
Author: Daniel McCarville
Author-email: daniel.mccarville@gmail.com
License: UNKNOWN
Platform: UNKNOWN
Classifier: Programming Language :: Python :: 3
Classifier: License :: OSI Approved :: MIT License
Classifier: Operating System :: OS Independent
Classifier: Intended Audience :: Financial and Insurance Industry
Classifier: Intended Audience :: Science/Research
Classifier: Topic :: Office/Business
Classifier: Topic :: Office/Business :: Financial :: Accounting
Classifier: Topic :: Scientific/Engineering
Requires-Python: >=3.6
